[
    {
        "text": "my first note"
    },
    {
        "text": "mynoooooooooooooooooooooooooooooooooooooooooooooooooooooooooooooooooooooote"
    },
    {
        "text": "a rather long note consisting of too many words"
    },
    {
        "text": "NotAShortNoteAndWhatWillYouSayAboutIt"
    },
    {
        "text": "Another_One_Very_Long_And_Silly_Note"
    },
    {
        "text": "how.many.else.notes.are.you.going.to.write"
    },
    {
        "text": "1.note"
    },
    {
        "text": "2.note"
    },
    {
        "text": "3.note"
    },
    {
        "text": "note 100"
    },
    {
        "text": "note 1000"
    },
    {
        "text": "note 10000"
    },
    {
        "text": "aaaa"
    },
    {
        "text": "bbb"
    },
    {
        "text": "cccccc"
    },
    {
        "text": "111"
    },
    {
        "text": "222"
    },
    {
        "text": "333"
    }
]